sequence_classifier/__about__.py
sequence_classifier/__init__.py
sequence_classifier/py.typed
sequence_classifier/semiring.py
sequence_classifier/crf/__init__.py
sequence_classifier/crf/core.py
sequence_classifier-0.1.4.dist-info/METADATA
sequence_classifier-0.1.4.dist-info/WHEEL
sequence_classifier-0.1.4.dist-info/licenses/LICENSE
sequence_classifier-0.1.4.dist-info/RECORD
