Metadata-Version: 2.1
Name: sequence-classifier
Version: 0.1.4
Author-email: Yasufumi Taniguchi <yasufumi.taniguchi@gmail.com>
License: MIT
License-File: LICENSE
Classifier: Programming Language :: Python
Classifier: Programming Language :: Python :: 3.8
Classifier: Programming Language :: Python :: 3.9
Classifier: Programming Language :: Python :: 3.10
Classifier: Programming Language :: Python :: 3.11
Requires-Python: <3.12,>=3.8
Requires-Dist: torch>=2.1.0
Provides-Extra: ci
Requires-Dist: black>=23.10.1; extra == 'ci'
Requires-Dist: hypothesis>=6.88.4; extra == 'ci'
Requires-Dist: mypy>=1.7.0; extra == 'ci'
Requires-Dist: pytest-cov>=4.1.0; extra == 'ci'
Requires-Dist: pytest>=7.4.3; extra == 'ci'
Requires-Dist: pytorch-crf>=0.7.2; extra == 'ci'
Requires-Dist: ruff>=0.1.3; extra == 'ci'
Requires-Dist: sequence-classifier[example]; extra == 'ci'
Requires-Dist: sequence-label>=0.1.6; extra == 'ci'
Requires-Dist: torch-struct>=0.5; extra == 'ci'
Provides-Extra: dev
Requires-Dist: ipdb>=0.13.13; extra == 'dev'
Requires-Dist: ipython>=8.12.3; extra == 'dev'
Requires-Dist: pdbpp>=0.10.3; extra == 'dev'
Provides-Extra: example
Requires-Dist: datasets>=2.15.0; extra == 'example'
Requires-Dist: evaluate>=0.4.1; extra == 'example'
Requires-Dist: seqeval>=1.2.2; extra == 'example'
Requires-Dist: transformers[torch]>=4.35.2; extra == 'example'
